COPYRIGHT
MANIFEST.in
setup.cfg
setup.py
docs/Makefile
docs/api_docs.rst
docs/conf.py
docs/index.rst
docs/make.bat
eurostat/__init__.py
eurostat/nuts.py
eurostat_rdf.egg-info/PKG-INFO
eurostat_rdf.egg-info/SOURCES.txt
eurostat_rdf.egg-info/dependency_links.txt
eurostat_rdf.egg-info/entry_points.txt
eurostat_rdf.egg-info/not-zip-safe
eurostat_rdf.egg-info/requires.txt
eurostat_rdf.egg-info/top_level.txt